peakviz/__init__.py
peakviz/__main__.py
peakviz/cli.py
peakviz/dataloader.py
peakviz/point_sensor.py
peakviz/pre_processing.py
peakviz/vizualization.py
peakviz-1.0.2.dist-info/licenses/LICENSE
peakviz-1.0.2.dist-info/METADATA
peakviz-1.0.2.dist-info/WHEEL
peakviz-1.0.2.dist-info/entry_points.txt
peakviz-1.0.2.dist-info/top_level.txt
peakviz-1.0.2.dist-info/RECORD
