Metadata-Version: 2.4
Name: peakviz
Version: 1.0.2
Summary: A tool to visualize Hyperspectral data from point and imaging sensors.
Author-email: Tasnim Tabassum Nova <tabassumnova1@gmail.com>
License: MIT License
Project-URL: Homepage, https://github.com/TabassumNova/PeakViz
Classifier: Programming Language :: Python :: 3
Classifier: License :: OSI Approved :: MIT License
Classifier: Operating System :: OS Independent
Requires-Python: >=3.8
License-File: LICENSE
Requires-Dist: PyQt5
Requires-Dist: numpy
Requires-Dist: matplotlib
Requires-Dist: pandas
Requires-Dist: plotly
Requires-Dist: nbformat
Requires-Dist: openpyxl
Dynamic: license-file
